{
  "found": [
    "ada",
    "assembly",
    "bash",
    "c",
    "c_",
    "c__",
    "cadence",
    "carbon",
    "clojure",
    "cobol",
    "cross",
    "crystal",
    "dart",
    "delphi",
    "elixir",
    "eon",
    "eon_bootstrap",
    "eon_kernel",
    "erlang",
    "f_",
    "fortran",
    "full_eon",
    "go",
    "haskell",
    "integrated_eon",
    "jai",
    "java",
    "javascript",
    "julia",
    "kotlin",
    "llvm_ir",
    "lua",
    "master_universal",
    "matlab",
    "motoko",
    "move",
    "multi_target",
    "n0mn0m_cross_platform",
    "n0mn0m_quantum_asm",
    "nim",
    "ocaml",
    "odin",
    "pascal",
    "perl",
    "php",
    "powershell",
    "python",
    "r",
    "reverser",
    "ruby",
    "rust",
    "scala",
    "self_contained",
    "self_hosted_eon",
    "solidity",
    "swift",
    "test_complete",
    "test_full_eon",
    "test_self_hosted",
    "typescript",
    "uber_elegant",
    "universal",
    "universal_cross_platform",
    "universal_multi_language",
    "v",
    "vb_net",
    "vyper",
    "webassembly",
    "zig"
  ],
  "missing": [
    "cpp",
    "csharp",
    "fsharp",
    "sql",
    "ml",
    "prolog",
    "scheme",
    "lisp",
    "dockerfile",
    "make",
    "json",
    "xml",
    "yaml",
    "ini",
    "toml",
    "markdown"
  ],
  "totalRequested": 63,
  "foundCount": 69,
  "missingCount": 16
}
