{"version":1,"resource":"file:///c%3A/Users/HiH8e/Downloads/RawrXD-production-lazy-init/src/qtapp/MainWindow_v5.cpp","entries":[{"id":"UXfK.cpp","source":"Chat Edit: 'Yes please fully continue with whatever is required to complete the task at hand without removal or deletion of any features/code IE only level or enhancing/expanding WITH the level, not leaving it behind!'","timestamp":1766991718163},{"id":"hs8X.cpp","source":"Chat Edit: '2025-12-29 02:17:12.775 [APP] main() start\r\n2025-12-29 02:17:12.787 [APP] QApplication constructed\r\n2025-12-29 02:17:12.787 [QtLog][DEBUG] Starting RawrXD-QtShell...\r\n2025-12-29 02:17:12.788 [APP] Starting RawrXD-QtShell...\r\n2025-12-29 02:17:12.788 [APP] Creating MainWindow...\r\n2025-12-29 02:17:12.788 [QtLog][DEBUG] Creating MainWindow...\r\n2025-12-29 02:17:12.932 [QtLog][DEBUG] [createTerminalPanel] Creating terminal panel with shell integration\r\n2025-12-29 02:17:12.948 [QtLog][DEBUG] [createTerminalPanel] Terminal panel created successfully\r\n2025-12-29 02:17:12.951 [QtLog][DEBUG] [createDebugPanel] Creating debug panel with log management\r\n2025-12-29 02:17:12.952 [QtLog][DEBUG] [createDebugPanel] Debug panel created successfully with 3 initial log entries\r\n2025-12-29 02:17:12.987 [APP] signal 11 received\r\n2025-12-29 02:17:12.987 [APP] signal 22 received\r\n2025-12-29 02:22:26.030 [APP] main() start\r\n2025-12-29 02:22:26.042 [APP] QApplication constructed\r\n2025-12-29 02:22:26.042 [QtLog][DEBUG] Starting RawrXD-QtShell...\r\n2025-12-29 02:22:26.042 [APP] Starting RawrXD-QtShell...\r\n2025-12-29 02:22:26.042 [APP] Creating MainWindow...\r\n2025-12-29 02:22:26.042 [QtLog][DEBUG] Creating MainWindow...\r\n2025-12-29 02:22:26.219 [QtLog][DEBUG] [createTerminalPanel] Creating terminal panel with shell integration\r\n2025-12-29 02:22:26.232 [QtLog][DEBUG] [createTerminalPanel] Terminal panel created successfully\r\n2025-12-29 02:22:26.235 [QtLog][DEBUG] [createDebugPanel] Creating debug panel with log management\r\n2025-12-29 02:22:26.238 [QtLog][DEBUG] [createDebugPanel] Debug panel created successfully with 3 initial log entries\r\n2025-12-29 02:22:26.279 [APP] signal 11 received\r\n2025-12-29 02:22:26.279 [APP] signal 22 received\r\n2025-12-29 02:33:39.030 [APP] main() start\r\n2025-12-29 02:33:39.042 [APP] QApplication constructed\r\n2025-12-29 02:33:39.042 [QtLog][DEBUG] Starting RawrXD-QtShell...\r\n2025-12-29 02:33:39.042 [APP] Starting RawrXD-QtShell...\r\n2025-12-29 02:33:39.042 [APP] Creating MainWindow...\r\n2025-12-29 02:33:39.042 [QtLog][DEBUG] Creating MainWindow...\r\n2025-12-29 02:33:39.221 [QtLog][DEBUG] [createTerminalPanel] Creating terminal panel with shell integration\r\n2025-12-29 02:33:39.236 [QtLog][DEBUG] [createTerminalPanel] Terminal panel created successfully\r\n2025-12-29 02:33:39.237 [QtLog][DEBUG] [createDebugPanel] Creating debug panel with log management\r\n2025-12-29 02:33:39.240 [QtLog][DEBUG] [createDebugPanel] Debug panel created successfully with 3 initial log entries\r\n2025-12-29 02:33:39.280 [APP] signal 11 received\r\n2025-12-29 02:33:39.280 [APP] signal 22 received\r\n2025-12-29 02:34:22.054 [APP] main() start\r\n2025-12-29 02:34:22.066 [APP] QApplication constructed\r\n2025-12-29 02:34:22.066 [QtLog][DEBUG] Starting RawrXD-QtShell...\r\n2025-12-29 02:34:22.066 [APP] Starting RawrXD-QtShell...\r\n2025-12-29 02:34:22.066 [APP] Creating MainWindow...\r\n2025-12-29 02:34:22.067 [QtLog][DEBUG] Creating MainWindow...\r\n2025-12-29 02:34:22.215 [QtLog][DEBUG] [createTerminalPanel] Creating terminal panel with shell integration\r\n2025-12-29 02:34:22.230 [QtLog][DEBUG] [createTerminalPanel] Terminal panel created successfully\r\n2025-12-29 02:34:22.233 [QtLog][DEBUG] [createDebugPanel] Creating debug panel with log management\r\n2025-12-29 02:34:22.235 [QtLog][DEBUG] [createDebugPanel] Debug panel created successfully with 3 initial log entries\r\n2025-12-29 02:34:22.270 [APP] signal 11 received\r\n2025-12-29 02:34:22.270 [APP] signal 22 received\r\n\r\n\r\nSame error'","timestamp":1766993773241},{"id":"wRaL.cpp","source":"Chat Edit: '2025-12-29 02:17:12.775 [APP] main() start\r\n2025-12-29 02:17:12.787 [APP] QApplication constructed\r\n2025-12-29 02:17:12.787 [QtLog][DEBUG] Starting RawrXD-QtShell...\r\n2025-12-29 02:17:12.788 [APP] Starting RawrXD-QtShell...\r\n2025-12-29 02:17:12.788 [APP] Creating MainWindow...\r\n2025-12-29 02:17:12.788 [QtLog][DEBUG] Creating MainWindow...\r\n2025-12-29 02:17:12.932 [QtLog][DEBUG] [createTerminalPanel] Creating terminal panel with shell integration\r\n2025-12-29 02:17:12.948 [QtLog][DEBUG] [createTerminalPanel] Terminal panel created successfully\r\n2025-12-29 02:17:12.951 [QtLog][DEBUG] [createDebugPanel] Creating debug panel with log management\r\n2025-12-29 02:17:12.952 [QtLog][DEBUG] [createDebugPanel] Debug panel created successfully with 3 initial log entries\r\n2025-12-29 02:17:12.987 [APP] signal 11 received\r\n2025-12-29 02:17:12.987 [APP] signal 22 received\r\n2025-12-29 02:22:26.030 [APP] main() start\r\n2025-12-29 02:22:26.042 [APP] QApplication constructed\r\n2025-12-29 02:22:26.042 [QtLog][DEBUG] Starting RawrXD-QtShell...\r\n2025-12-29 02:22:26.042 [APP] Starting RawrXD-QtShell...\r\n2025-12-29 02:22:26.042 [APP] Creating MainWindow...\r\n2025-12-29 02:22:26.042 [QtLog][DEBUG] Creating MainWindow...\r\n2025-12-29 02:22:26.219 [QtLog][DEBUG] [createTerminalPanel] Creating terminal panel with shell integration\r\n2025-12-29 02:22:26.232 [QtLog][DEBUG] [createTerminalPanel] Terminal panel created successfully\r\n2025-12-29 02:22:26.235 [QtLog][DEBUG] [createDebugPanel] Creating debug panel with log management\r\n2025-12-29 02:22:26.238 [QtLog][DEBUG] [createDebugPanel] Debug panel created successfully with 3 initial log entries\r\n2025-12-29 02:22:26.279 [APP] signal 11 received\r\n2025-12-29 02:22:26.279 [APP] signal 22 received\r\n2025-12-29 02:33:39.030 [APP] main() start\r\n2025-12-29 02:33:39.042 [APP] QApplication constructed\r\n2025-12-29 02:33:39.042 [QtLog][DEBUG] Starting RawrXD-QtShell...\r\n2025-12-29 02:33:39.042 [APP] Starting RawrXD-QtShell...\r\n2025-12-29 02:33:39.042 [APP] Creating MainWindow...\r\n2025-12-29 02:33:39.042 [QtLog][DEBUG] Creating MainWindow...\r\n2025-12-29 02:33:39.221 [QtLog][DEBUG] [createTerminalPanel] Creating terminal panel with shell integration\r\n2025-12-29 02:33:39.236 [QtLog][DEBUG] [createTerminalPanel] Terminal panel created successfully\r\n2025-12-29 02:33:39.237 [QtLog][DEBUG] [createDebugPanel] Creating debug panel with log management\r\n2025-12-29 02:33:39.240 [QtLog][DEBUG] [createDebugPanel] Debug panel created successfully with 3 initial log entries\r\n2025-12-29 02:33:39.280 [APP] signal 11 received\r\n2025-12-29 02:33:39.280 [APP] signal 22 received\r\n2025-12-29 02:34:22.054 [APP] main() start\r\n2025-12-29 02:34:22.066 [APP] QApplication constructed\r\n2025-12-29 02:34:22.066 [QtLog][DEBUG] Starting RawrXD-QtShell...\r\n2025-12-29 02:34:22.066 [APP] Starting RawrXD-QtShell...\r\n2025-12-29 02:34:22.066 [APP] Creating MainWindow...\r\n2025-12-29 02:34:22.067 [QtLog][DEBUG] Creating MainWindow...\r\n2025-12-29 02:34:22.215 [QtLog][DEBUG] [createTerminalPanel] Creating terminal panel with shell integration\r\n2025-12-29 02:34:22.230 [QtLog][DEBUG] [createTerminalPanel] Terminal panel created successfully\r\n2025-12-29 02:34:22.233 [QtLog][DEBUG] [createDebugPanel] Creating debug panel with log management\r\n2025-12-29 02:34:22.235 [QtLog][DEBUG] [createDebugPanel] Debug panel created successfully with 3 initial log entries\r\n2025-12-29 02:34:22.270 [APP] signal 11 received\r\n2025-12-29 02:34:22.270 [APP] signal 22 received\r\n2025-12-29 02:36:24.371 [APP] main() start\r\n2025-12-29 02:36:24.382 [APP] QApplication constructed\r\n2025-12-29 02:36:24.383 [QtLog][DEBUG] Starting RawrXD-QtShell...\r\n2025-12-29 02:36:24.383 [APP] Starting RawrXD-QtShell...\r\n2025-12-29 02:36:24.383 [APP] Creating MainWindow...\r\n2025-12-29 02:36:24.383 [QtLog][DEBUG] Creating MainWindow...\r\n2025-12-29 02:36:24.541 [QtLog][DEBUG] [createTerminalPanel] Creating terminal panel with shell integration\r\n2025-12-29 02:36:24.553 [QtLog][DEBUG] [createTerminalPanel] Terminal panel created successfully\r\n2025-12-29 02:36:24.556 [QtLog][DEBUG] [createDebugPanel] Creating debug panel with log management\r\n2025-12-29 02:36:24.558 [QtLog][DEBUG] [createDebugPanel] Debug panel created successfully with 3 initial log entries\r\n2025-12-29 02:36:24.594 [APP] signal 11 received\r\n2025-12-29 02:36:24.594 [APP] signal 22 received\r\n2025-12-29 02:36:42.649 [APP] main() start\r\n2025-12-29 02:36:42.661 [APP] QApplication constructed\r\n2025-12-29 02:36:42.662 [QtLog][DEBUG] Starting RawrXD-QtShell...\r\n2025-12-29 02:36:42.662 [APP] Starting RawrXD-QtShell...\r\n2025-12-29 02:36:42.662 [APP] Creating MainWindow...\r\n2025-12-29 02:36:42.662 [QtLog][DEBUG] Creating MainWindow...\r\n2025-12-29 02:36:42.810 [QtLog][DEBUG] [createTerminalPanel] Creating terminal panel with shell integration\r\n2025-12-29 02:36:42.825 [QtLog][DEBUG] [createTerminalPanel] Terminal panel created successfully\r\n2025-12-29 02:36:42.826 [QtLog][DEBUG] [createDebugPanel] Creating debug panel with log management\r\n2025-12-29 02:36:42.830 [QtLog][DEBUG] [createDebugPanel] Debug panel created successfully with 3 initial log entries\r\n2025-12-29 02:36:42.863 [APP] signal 11 received\r\n2025-12-29 02:36:42.863 [APP] signal 22 received\r\n2025-12-29 02:17:12.775 [APP] main() start\r\n2025-12-29 02:17:12.787 [APP] QApplication constructed\r\n2025-12-29 02:17:12.787 [QtLog][DEBUG] Starting RawrXD-QtShell...\r\n2025-12-29 02:17:12.788 [APP] Starting RawrXD-QtShell...\r\n2025-12-29 02:17:12.788 [APP] Creating MainWindow...\r\n2025-12-29 02:17:12.788 [QtLog][DEBUG] Creating MainWindow...\r\n2025-12-29 02:17:12.932 [QtLog][DEBUG] [createTerminalPanel] Creating terminal panel with shell integration\r\n2025-12-29 02:17:12.948 [QtLog][DEBUG] [createTerminalPanel] Terminal panel created successfully\r\n2025-12-29 02:17:12.951 [QtLog][DEBUG] [createDebugPanel] Creating debug panel with log management\r\n2025-12-29 02:17:12.952 [QtLog][DEBUG] [createDebugPanel] Debug panel created successfully with 3 initial log entries\r\n2025-12-29 02:17:12.987 [APP] signal 11 received\r\n2025-12-29 02:17:12.987 [APP] signal 22 received\r\n2025-12-29 02:22:26.030 [APP] main() start\r\n2025-12-29 02:22:26.042 [APP] QApplication constructed\r\n2025-12-29 02:22:26.042 [QtLog][DEBUG] Starting RawrXD-QtShell...\r\n2025-12-29 02:22:26.042 [APP] Starting RawrXD-QtShell...\r\n2025-12-29 02:22:26.042 [APP] Creating MainWindow...\r\n2025-12-29 02:22:26.042 [QtLog][DEBUG] Creating MainWindow...\r\n2025-12-29 02:22:26.219 [QtLog][DEBUG] [createTerminalPanel] Creating terminal panel with shell integration\r\n2025-12-29 02:22:26.232 [QtLog][DEBUG] [createTerminalPanel] Terminal panel created successfully\r\n2025-12-29 02:22:26.235 [QtLog][DEBUG] [createDebugPanel] Creating debug panel with log management\r\n2025-12-29 02:22:26.238 [QtLog][DEBUG] [createDebugPanel] Debug panel created successfully with 3 initial log entries\r\n2025-12-29 02:22:26.279 [APP] signal 11 received\r\n2025-12-29 02:22:26.279 [APP] signal 22 received\r\n2025-12-29 02:33:39.030 [APP] main() start\r\n2025-12-29 02:33:39.042 [APP] QApplication constructed\r\n2025-12-29 02:33:39.042 [QtLog][DEBUG] Starting RawrXD-QtShell...\r\n2025-12-29 02:33:39.042 [APP] Starting RawrXD-QtShell...\r\n2025-12-29 02:33:39.042 [APP] Creating MainWindow...\r\n2025-12-29 02:33:39.042 [QtLog][DEBUG] Creating MainWindow...\r\n2025-12-29 02:33:39.221 [QtLog][DEBUG] [createTerminalPanel] Creating terminal panel with shell integration\r\n2025-12-29 02:33:39.236 [QtLog][DEBUG] [createTerminalPanel] Terminal panel created successfully\r\n2025-12-29 02:33:39.237 [QtLog][DEBUG] [createDebugPanel] Creating debug panel with log management\r\n2025-12-29 02:33:39.240 [QtLog][DEBUG] [createDebugPanel] Debug panel created successfully with 3 initial log entries\r\n2025-12-29 02:33:39.280 [APP] signal 11 received\r\n2025-12-29 02:33:39.280 [APP] signal 22 received\r\n2025-12-29 02:34:22.054 [APP] main() start\r\n2025-12-29 02:34:22.066 [APP] QApplication constructed\r\n2025-12-29 02:34:22.066 [QtLog][DEBUG] Starting RawrXD-QtShell...\r\n2025-12-29 02:34:22.066 [APP] Starting RawrXD-QtShell...\r\n2025-12-29 02:34:22.066 [APP] Creating MainWindow...\r\n2025-12-29 02:34:22.067 [QtLog][DEBUG] Creating MainWindow...\r\n2025-12-29 02:34:22.215 [QtLog][DEBUG] [createTerminalPanel] Creating terminal panel with shell integration\r\n2025-12-29 02:34:22.230 [QtLog][DEBUG] [createTerminalPanel] Terminal panel created successfully\r\n2025-12-29 02:34:22.233 [QtLog][DEBUG] [createDebugPanel] Creating debug panel with log management\r\n2025-12-29 02:34:22.235 [QtLog][DEBUG] [createDebugPanel] Debug panel created successfully with 3 initial log entries\r\n2025-12-29 02:34:22.270 [APP] signal 11 received\r\n2025-12-29 02:34:22.270 [APP] signal 22 received\r\n2025-12-29 02:36:24.371 [APP] main() start\r\n2025-12-29 02:36:24.382 [APP] QApplication constructed\r\n2025-12-29 02:36:24.383 [QtLog][DEBUG] Starting RawrXD-QtShell...\r\n2025-12-29 02:36:24.383 [APP] Starting RawrXD-QtShell...\r\n2025-12-29 02:36:24.383 [APP] Creating MainWindow...\r\n2025-12-29 02:36:24.383 [QtLog][DEBUG] Creating MainWindow...\r\n2025-12-29 02:36:24.541 [QtLog][DEBUG] [createTerminalPanel] Creating terminal panel with shell integration\r\n2025-12-29 02:36:24.553 [QtLog][DEBUG] [createTerminalPanel] Terminal panel created successfully\r\n2025-12-29 02:36:24.556 [QtLog][DEBUG] [createDebugPanel] Creating debug panel with log management\r\n2025-12-29 02:36:24.558 [QtLog][DEBUG] [createDebugPanel] Debug panel created successfully with 3 initial log entries\r\n2025-12-29 02:36:24.594 [APP] signal 11 received\r\n2025-12-29 02:36:24.594 [APP] signal 22 received\r\n2025-12-29 02:36:42.649 [APP] main() start\r\n2025-12-29 02:36:42.661 [APP] QApplication constructed\r\n2025-12-29 02:36:42.662 [QtLog][DEBUG] Starting RawrXD-QtShell...\r\n2025-12-29 02:36:42.662 [APP] Starting RawrXD-QtShell...\r\n2025-12-29 02:36:42.662 [APP] Creating MainWindow...\r\n2025-12-29 02:36:42.662 [QtLog][DEBUG] Creating MainWindow...\r\n2025-12-29 02:36:42.810 [QtLog][DEBUG] [createTerminalPanel] Creating terminal panel with shell integration\r\n2025-12-29 02:36:42.825 [QtLog][DEBUG] [createTerminalPanel] Terminal panel created successfully\r\n2025-12-29 02:36:42.826 [QtLog][DEBUG] [createDebugPanel] Creating debug panel with log management\r\n2025-12-29 02:36:42.830 [QtLog][DEBUG] [createDebugPanel] Debug panel created successfully with 3 initial log entries\r\n2025-12-29 02:36:42.863 [APP] signal 11 received\r\n2025-12-29 02:36:42.863 [APP] signal 22 received\r\n'","timestamp":1766993851751},{"id":"KmqR.cpp","source":"Chat Edit: 'and have it on the bottom of the IDE where it can flash when a model is being used what the latency is actually is next to where teh ram useage is located on the bottom left panel of the IDE\r\n or create a pane that has full statistics and include that as well'","timestamp":1766994378665},{"id":"QHzs.cpp","source":"Chat Edit: 'and have it on the bottom of the IDE where it can flash when a model is being used what the latency is actually is next to where teh ram useage is located on the bottom left panel of the IDE\r\n or create a pane that has full statistics and include that as well'","timestamp":1766994389806}]}