{"version":1,"resource":"file:///c%3A/Users/HiH8e/Downloads/RawrXD-production-lazy-init/src/qtapp/latency_status_panel.cpp","entries":[{"id":"Hgqa.cpp","source":"Chat Edit: 'and have it on the bottom of the IDE where it can flash when a model is being used what the latency is actually is next to where teh ram useage is located on the bottom left panel of the IDE\r\n or create a pane that has full statistics and include that as well'","timestamp":1766994362106},{"id":"kSCl.cpp","source":"Chat Edit: 'Fully fix it , its to see the real complete distance between the model thats loaded and our front end where we communicate'","timestamp":1766994763556}]}