{"version":1,"resource":"file:///c%3A/Users/HiH8e/OneDrive/Desktop/RawrXD-production-lazy-init/masm_ide/src/gguf_loader_settings.asm","entries":[{"id":"sqlh.asm","source":"Chat Edit: '; pifabric_core.asm\r\n.386\r\n.model flat, stdcall\r\noption casemap:none\r\n\r\ninclude windows.inc\r\ninclude kernel32.inc\r\n\r\nincludelib kernel32.lib\r\n\r\nEXTERN  GGUFChain_LoadModel:PROC\r\nEXTERN  GGUFChain_CloseModel:PROC\r\nEXTERN  GGUFChain_StreamChunk:PROC\r\n\r\nPUBLIC  PiFabric_Init\r\nPUBLIC  PiFabric_Open\r\nPUBLIC  PiFabric_Stream\r\nPUBLIC  PiFabric_Close\r\n\r\nPiFabricHandle STRUCT\r\n    hChain      DWORD ?\r\n    pChain      DWORD ?\r\n    dwMethod    DWORD ?\r\n    dwChainMode DWORD ?\r\n    dwTier      DWORD ?\r\n    dwFlags     DWORD ?\r\nPiFabricHandle ENDS\r\n\r\n.data\r\ng_dwPiFabricInitFlag dd 0\r\n\r\n.code\r\n\r\nPiFabric_Init PROC\r\n\r\n    mov eax, g_dwPiFabricInitFlag\r\n    test eax, eax\r\n    jnz  @done\r\n\r\n    mov eax, 1\r\n    mov g_dwPiFabricInitFlag, eax\r\n\r\n@done:\r\n    mov eax, 1\r\n    ret\r\nPiFabric_Init ENDP\r\n\r\nPiFabric_Open PROC USES esi edi ebx lpPath:DWORD, dwMethodMask:DWORD, dwChainMode:DWORD\r\n\r\n    call PiFabric_Init\r\n\r\n    push dwChainMode\r\n    push dwMethodMask\r\n    push lpPath\r\n    call GGUFChain_LoadModel\r\n    test eax, eax\r\n    jz  @fail\r\n    mov esi, eax\r\n\r\n    push SIZEOF PiFabricHandle\r\n    push GMEM_ZEROINIT\r\n    call GlobalAlloc\r\n    test eax, eax\r\n    jz  @close_chain\r\n    mov edi, eax\r\n\r\n    mov [edi].PiFabricHandle.hChain,    esi\r\n    mov [edi].PiFabricHandle.pChain,    esi\r\n    mov [edi].PiFabricHandle.dwMethod,  dwMethodMask\r\n    mov [edi].PiFabricHandle.dwChainMode,dwChainMode\r\n    mov [edi].PiFabricHandle.dwTier,    0\r\n    mov [edi].PiFabricHandle.dwFlags,   1\r\n\r\n    mov eax, edi\r\n    ret\r\n\r\n@close_chain:\r\n    push esi\r\n    call GGUFChain_CloseModel\r\n\r\n@fail:\r\n    xor eax, eax\r\n    ret\r\n\r\nPiFabric_Open ENDP\r\n\r\nPiFabric_Stream PROC USES esi edi ebx hFabric:DWORD, pDst:DWORD, dwBytes:DWORD\r\n\r\n    mov esi, hFabric\r\n    test esi, esi\r\n    jz  @fail\r\n\r\n    mov eax, [esi].PiFabricHandle.hChain\r\n    test eax, eax\r\n    jz  @fail\r\n\r\n    push dwBytes\r\n    push pDst\r\n    push eax\r\n    call GGUFChain_StreamChunk\r\n    ret\r\n\r\n@fail:\r\n    xor eax, eax\r\n    ret\r\n\r\nPiFabric_Stream ENDP\r\n\r\nPiFabric_Close PROC USES esi hFabric:DWORD\r\n\r\n    mov esi, hFabric\r\n    test esi, esi\r\n    jz  @done\r\n\r\n    mov eax, [esi].PiFabricHandle.hChain\r\n    test eax, eax\r\n    jz  @free_only\r\n\r\n    push eax\r\n    call GGUFChain_CloseModel\r\n\r\n@free_only:\r\n    push esi\r\n    call GlobalFree\r\n\r\n@done:\r\n    xor eax, eax\r\n    ret\r\n\r\nPiFabric_Close ENDP\r\n\r\nEND'","timestamp":1766354004993}]}